LICENSE
MANIFEST.in
README.rst
requirements.txt
setup.cfg
setup.py
src/os_tornado/VERSION
src/os_tornado/__init__.py
src/os_tornado/cmdline.py
src/os_tornado/component_manager.py
src/os_tornado/exceptions.py
src/os_tornado/extension.py
src/os_tornado/log.py
src/os_tornado/request_handler_manager.py
src/os_tornado/runner.py
src/os_tornado.egg-info/PKG-INFO
src/os_tornado.egg-info/SOURCES.txt
src/os_tornado.egg-info/dependency_links.txt
src/os_tornado.egg-info/entry_points.txt
src/os_tornado.egg-info/not-zip-safe
src/os_tornado.egg-info/requires.txt
src/os_tornado.egg-info/top_level.txt
src/os_tornado/commands/__init__.py
src/os_tornado/commands/list.py
src/os_tornado/commands/runserver.py
src/os_tornado/commands/startproject.py
src/os_tornado/commands/version.py
src/os_tornado/commands/project_template/manager.py.tpl
src/os_tornado/commands/project_template/app/__init__.py.tpl
src/os_tornado/commands/project_template/app/settings.py.tpl
src/os_tornado/commands/project_template/app/extensions/__init__.py
src/os_tornado/commands/project_template/app/extensions/example_extension.py.tpl
src/os_tornado/commands/project_template/app/request_handlers/__init__.py
src/os_tornado/commands/project_template/app/request_handlers/example_handler.py.tpl
src/os_tornado/decorators/__init__.py
src/os_tornado/decorators/json_response.py
src/os_tornado/settings/__init__.py
src/os_tornado/settings/default_settings.py
src/os_tornado/utils/__init__.py
src/os_tornado/utils/module_utils.py
src/os_tornado/utils/signal_utils.py
tests/__init__.py
tests/test_jsonify.py
tests/test_log.py
tests/test_settings.py
tests/test_signal_utils.py
tests/test_commands/__init__.py
tests/test_commands/cmd.py
tests/test_commands/settings.py
tests/test_commands/temp_extension.py
tests/test_commands/temp_handler.py
tests/test_commands/test_cmd.py
tests/test_module_utils/__init__.py
tests/test_module_utils/test_module_utils.py
tests/test_module_utils/test_mod/__init__.py
tests/test_module_utils/test_mod/class_a.py
tests/test_module_utils/test_mod/class_b.py
tests/test_module_utils/test_mod0/__init__.py
tests/test_module_utils/test_mod0/test_mod1/__init__.py